ros2_llcb/__init__.py
ros2_llcb/ros2_llcb.py
ros2_llcb-0.0.5.dist-info/LICENCE
ros2_llcb-0.0.5.dist-info/METADATA
ros2_llcb-0.0.5.dist-info/WHEEL
ros2_llcb-0.0.5.dist-info/top_level.txt
ros2_llcb-0.0.5.dist-info/RECORD
