Metadata-Version: 2.1
Name: ros2-llcb
Version: 0.0.5
Summary: ROS2 log level callback.
Home-page: https://github.com/pypa/ros2_llcb
Author: Michael Ramos
Author-email: mike.ramos58@gmail.com
License: UNKNOWN
Platform: UNKNOWN
Classifier: Programming Language :: Python :: 3
Classifier: License :: OSI Approved :: MIT License
Classifier: Operating System :: OS Independent
